xsuite/__init__.py
xsuite/cli.py
xsuite/kernel_definitions.py
xsuite/prebuild_kernels.py
xsuite/lib/__init__.py
xsuite/lib/default_base_config.c
xsuite/lib/default_base_config.cpython-312-x86_64-linux-gnu.so
xsuite/lib/default_base_config.json
xsuite/lib/default_no_config.c
xsuite/lib/default_no_config.cpython-312-x86_64-linux-gnu.so
xsuite/lib/default_no_config.json
xsuite/lib/non_tracking_kernels.c
xsuite/lib/non_tracking_kernels.cpython-312-x86_64-linux-gnu.so
xsuite/lib/non_tracking_kernels.json
xsuite/lib/only_xtrack_with_synrad.c
xsuite/lib/only_xtrack_with_synrad.cpython-312-x86_64-linux-gnu.so
xsuite/lib/only_xtrack_with_synrad.json
xsuite-0.45.17.dist-info/METADATA
xsuite-0.45.17.dist-info/WHEEL
xsuite-0.45.17.dist-info/entry_points.txt
xsuite-0.45.17.dist-info/top_level.txt
xsuite-0.45.17.dist-info/RECORD
xsuite-0.45.17.dist-info/licenses/LICENSE
