Metadata-Version: 2.4
Name: xsuite
Version: 0.45.17
Summary: Integrated suite for particle accelerator simulations.
Author: Riccardo De Maria, Giovanni Iadarola, Szymon Łopaciuk, et al.
License-Expression: Apache-2.0
Project-URL: Download, https://pypi.python.org/pypi/xsuite
Project-URL: Bug Tracker, https://github.com/xsuite/xsuite/issues
Project-URL: Documentation, https://xsuite.readthedocs.io/
Project-URL: Source Code, https://github.com/xsuite/xsuite
Requires-Python: >=3.10
License-File: LICENSE
Requires-Dist: xtrack==0.98.14
Requires-Dist: xfields==0.25.9
Requires-Dist: xcoll==0.9.4
Requires-Dist: xobjects==0.5.12
Requires-Dist: xdeps==0.10.11
Requires-Dist: xpart==0.23.8
Provides-Extra: notebooks
Requires-Dist: jupyter; extra == "notebooks"
Requires-Dist: ipympl; extra == "notebooks"
Requires-Dist: xplt; extra == "notebooks"
Provides-Extra: full-env
Requires-Dist: cpymad; extra == "full-env"
Requires-Dist: nafflib; extra == "full-env"
Requires-Dist: pytest; extra == "full-env"
Requires-Dist: pytest-mock; extra == "full-env"
Requires-Dist: jupyter; extra == "full-env"
Requires-Dist: ipympl; extra == "full-env"
Requires-Dist: xplt; extra == "full-env"
Requires-Dist: ipython; extra == "full-env"
Dynamic: license-file
